[
    {
        "id": 0,
        "image": "E A R L C U D Y W K",
        "RowType": 0,
        "CharType": 0
    },
    {
        "id": 1,
        "image": "I O T P M H V X Z",
        "RowType": 0,
        "CharType": 1
    },
    {
        "id": 2,
        "image": "N S G B F J Q",
        "RowType": 0,
        "CharType": 2,
    },
    {
        "id": 3,
        "image": "e a r l c u d y w k",
        "RowType": 3,
        "CharType": 9
    },
    {
        "id": 4,
        "image": "i o t p m h v x z",
        "RowType": 3,
        "CharType": 10
    },
    {
        "id": 5,
        "image": "n s g b f j q",
        "RowType": 3,
        "CharType": 11
    },
    {
        "id": 6,
        "image": "- / : ; ( ) $ & @ \"",
        "RowType": 1,
        "CharType": 3
    },
    {
        "id": 7,
        "image": "[ ] { } # % ^ * + =",
        "RowType": 1,
        "CharType": 4
    },
    {
        "id": 8,
        "image": "_ \\ | ~ < > € £ ¥ •",
        "RowType": 1,
        "CharType": 5
    },
    {
        "id": 9,
        "image": ". , ? ! '",
        "RowType": 1,
        "CharType": 6
    },
    {
        "id": 10,
        "image": "0 1 2 3 4",
        "RowType": 2,
        "CharType": 7
    },
    {
        "id": 11,
        "image": "5 6 7 8 9",
        "RowType": 2,
        "CharType": 8
    }
]

